uform/__init__.py
uform/chat.py
uform/gen_model.py
uform/numpy_processors.py
uform/onnx_encoders.py
uform/shared.py
uform/torch_decoders.py
uform/torch_encoders.py
uform/torch_processors.py
uform-3.1.3.dist-info/licenses/LICENSE
uform-3.1.3.dist-info/METADATA
uform-3.1.3.dist-info/WHEEL
uform-3.1.3.dist-info/entry_points.txt
uform-3.1.3.dist-info/top_level.txt
uform-3.1.3.dist-info/RECORD
