Metadata-Version: 2.4
Name: uform
Version: 3.1.3
Summary: Pocket-Sized Multimodal AI for Content Understanding and Generation
Author-email: Ash Vardanian <ash.vardanian@unum.cloud>, Mikhail Kim <mike.kim@unum.cloud>, Vladimir Orshulevich <vladimir.orshulevich@unum.cloud>
Maintainer-email: Unum Cloud <info@unum.cloud>
Project-URL: Homepage, https://github.com/unum-cloud/uform
Classifier: Development Status :: 5 - Production/Stable
Classifier: License :: OSI Approved :: Apache Software License
Classifier: Natural Language :: Chinese (Simplified)
Classifier: Natural Language :: English
Classifier: Natural Language :: French
Classifier: Natural Language :: German
Classifier: Natural Language :: Italian
Classifier: Natural Language :: Japanese
Classifier: Natural Language :: Korean
Classifier: Natural Language :: Polish
Classifier: Natural Language :: Russian
Classifier: Natural Language :: Spanish
Classifier: Natural Language :: Turkish
Classifier: Operating System :: OS Independent
Classifier: Programming Language :: Python :: 3
Classifier: Topic :: Scientific/Engineering :: Artificial Intelligence
Classifier: Topic :: Scientific/Engineering :: Image Processing
Classifier: Topic :: Scientific/Engineering :: Image Recognition
Requires-Python: >=3.7
License-File: LICENSE
Requires-Dist: huggingface_hub>=0.16.4
Requires-Dist: tokenizers>=0.13.3
Requires-Dist: pillow
Requires-Dist: simsimd
Provides-Extra: torch
Requires-Dist: torch>=1.13.1; extra == "torch"
Requires-Dist: torchvision; extra == "torch"
Requires-Dist: transformers<4.49.0,>=4.36.2; extra == "torch"
Provides-Extra: onnx
Requires-Dist: onnx>=1.15.0; extra == "onnx"
Requires-Dist: onnxruntime>=1.17.1; extra == "onnx"
Requires-Dist: numpy; extra == "onnx"
Provides-Extra: onnx-gpu
Requires-Dist: onnx>=1.15.0; extra == "onnx-gpu"
Requires-Dist: onnxruntime-gpu>=1.17.1; extra == "onnx-gpu"
Requires-Dist: numpy; extra == "onnx-gpu"
Provides-Extra: dev
Requires-Dist: pytest; extra == "dev"
Requires-Dist: pandas; extra == "dev"
Dynamic: license-file
